henry/__init__.py
henry/collection.py
henry/core.py
henry/exceptions.py
henry/product.py
henry/source.py
hippoclient/__init__.py
hippoclient/caching.py
hippoclient/cli.py
hippoclient/collections.py
hippoclient/core.py
hippoclient/downloads.py
hippoclient/helper.py
hippoclient/product.py
hippoclient/relationships.py
hippoclient/textedit.py
hippoclient/tools.py
hippometa/__init__.py
hippometa/archive.py
hippometa/base.py
hippometa/beam.py
hippometa/cameras.py
hippometa/catalog.py
hippometa/mapset.py
hippometa/numeric.py
hippometa/simple.py
hipposerve/__init__.py
hipposerve/settings.py
hipposerve/api/__init__.py
hipposerve/api/app.py
hipposerve/api/product.py
hipposerve/api/relationships.py
hipposerve/api/soauth.py
hipposerve/api/models/groups.py
hipposerve/api/models/product.py
hipposerve/api/models/relationships.py
hipposerve/api/models/users.py
hipposerve/database/__init__.py
hipposerve/service/__init__.py
hipposerve/service/acl.py
hipposerve/service/auth.py
hipposerve/service/collection.py
hipposerve/service/product.py
hipposerve/service/storage.py
hipposerve/service/users.py
hipposerve/service/utils.py
hipposerve/service/versioning.py
hipposerve/storage/__init__.py
hipposerve/web/__init__.py
hipposerve/web/auth.py
hipposerve/web/router.py
hipposerve/web/search.py
hipposerve/web/static/apple-touch-icon.png
hipposerve/web/static/favicon.ico
hipposerve/web/static/logo.svg
hipposerve/web/templates/404.html
hipposerve/web/templates/apikey.html
hipposerve/web/templates/collection.html
hipposerve/web/templates/collection_edit.html
hipposerve/web/templates/core.html
hipposerve/web/templates/index.html
hipposerve/web/templates/login.html
hipposerve/web/templates/navigation.html
hipposerve/web/templates/parent_child_diagram.html
hipposerve/web/templates/product.html
hipposerve/web/templates/product_edit.html
hipposerve/web/templates/search_metadata.html
hipposerve/web/templates/search_results.html
hipposerve/web/templates/user.html
pyhippo-0.2.10.dist-info/licenses/LICENSE
pyhippo-0.2.10.dist-info/METADATA
pyhippo-0.2.10.dist-info/WHEEL
pyhippo-0.2.10.dist-info/entry_points.txt
pyhippo-0.2.10.dist-info/top_level.txt
pyhippo-0.2.10.dist-info/RECORD
