Metadata-Version: 2.4
Name: pyhippo
Version: 0.2.10
Summary: The Hierarchical Product Post Office, developed for the Simons Observatory.
Author: Jeremy Myers, Divesh Jain
Author-email: Josh Borrow <josh@joshborow.com>
License-Expression: MIT
Project-URL: Repository, https://github.com/simonsobs/hippo.git
Project-URL: Issues, https://github.com/simonsobs/hippo/issues
Classifier: Development Status :: 4 - Beta
Classifier: Intended Audience :: Science/Research
Classifier: Topic :: Software Development :: Build Tools
Classifier: Topic :: Scientific/Engineering :: Astronomy
Requires-Python: >=3.11
License-File: LICENSE
Requires-Dist: pydantic<2.11
Requires-Dist: pydantic-settings
Requires-Dist: anyio<4.1.0
Requires-Dist: asyncer
Requires-Dist: fastapi
Requires-Dist: uvicorn
Requires-Dist: beanie>=2.0.0
Requires-Dist: minio
Requires-Dist: jinja2
Requires-Dist: xxhash
Requires-Dist: jinja-markdown
Requires-Dist: typer
Requires-Dist: httpx
Requires-Dist: astropy
Requires-Dist: pyjwt
Requires-Dist: pwdlib[argon2]
Requires-Dist: python-multipart
Requires-Dist: loguru
Requires-Dist: tqdm
Requires-Dist: pymongo
Requires-Dist: textual[syntax]
Requires-Dist: soauth>=0.5.2
Provides-Extra: dev
Requires-Dist: pytest; extra == "dev"
Requires-Dist: ruff; extra == "dev"
Requires-Dist: testcontainers; extra == "dev"
Requires-Dist: coverage; extra == "dev"
Requires-Dist: pytest-cov; extra == "dev"
Requires-Dist: pytest-asyncio; extra == "dev"
Requires-Dist: pytest-xprocess; extra == "dev"
Dynamic: license-file
